zarban/__init__.py
zarban/service/__init__.py
zarban/service/setup.py
zarban/service/openapi_client/__init__.py
zarban/service/openapi_client/api_client.py
zarban/service/openapi_client/configuration.py
zarban/service/openapi_client/exceptions.py
zarban/service/openapi_client/rest.py
zarban/service/openapi_client/api/__init__.py
zarban/service/openapi_client/api/accounts_api.py
zarban/service/openapi_client/api/addresses_api.py
zarban/service/openapi_client/api/borrows_api.py
zarban/service/openapi_client/api/collector_api.py
zarban/service/openapi_client/api/deposits_api.py
zarban/service/openapi_client/api/ilks_api.py
zarban/service/openapi_client/api/lending_pool_api.py
zarban/service/openapi_client/api/logs_api.py
zarban/service/openapi_client/api/orders_api.py
zarban/service/openapi_client/api/permit_api.py
zarban/service/openapi_client/api/points_api.py
zarban/service/openapi_client/api/prices_api.py
zarban/service/openapi_client/api/stable_coin_system_api.py
zarban/service/openapi_client/api/staking_api.py
zarban/service/openapi_client/api/swap_api.py
zarban/service/openapi_client/api/vaults_api.py
zarban/service/openapi_client/api/websocket_api.py
zarban/service/openapi_client/models/__init__.py
zarban/service/openapi_client/models/account.py
zarban/service/openapi_client/models/account_lendingpool_summary.py
zarban/service/openapi_client/models/account_stablecoin_system_summary.py
zarban/service/openapi_client/models/account_staking_summary.py
zarban/service/openapi_client/models/address.py
zarban/service/openapi_client/models/address_response.py
zarban/service/openapi_client/models/balance.py
zarban/service/openapi_client/models/basic_event.py
zarban/service/openapi_client/models/chain_activity.py
zarban/service/openapi_client/models/chain_activity_step.py
zarban/service/openapi_client/models/chain_activity_step_data.py
zarban/service/openapi_client/models/dutch_amount.py
zarban/service/openapi_client/models/eip712_sign_request.py
zarban-0.5.7.dist-info/LICENSE
zarban-0.5.7.dist-info/METADATA
zarban-0.5.7.dist-info/WHEEL
zarban-0.5.7.dist-info/top_level.txt
zarban-0.5.7.dist-info/RECORD
