Metadata-Version: 2.1
Name: zarban
Version: 0.5.7
Summary: Python SDK for Zarban
Home-page: https://github.com/zarbanio/zarban-py
Author: Zarban
Author-email: info@zarban.io
Project-URL: Homepage, https://zarban.io
Project-URL: Documentation, https://docs.zarban.io
Project-URL: Source Code, https://github.com/zarbanio/zarban-py
Project-URL: GitHub, https://github.com/zarbanio
Project-URL: Instagram, https://www.instagram.com/zarban_io/
Project-URL: X, https://twitter.com/ZarbanProtocol
Classifier: Development Status :: 3 - Alpha
Classifier: Intended Audience :: Developers
Classifier: License :: OSI Approved :: MIT License
Classifier: Operating System :: OS Independent
Classifier: Programming Language :: Python :: 3
Classifier: Programming Language :: Python :: 3.7
Classifier: Programming Language :: Python :: 3.8
Classifier: Programming Language :: Python :: 3.9
Requires-Python: >=3.7
License-File: LICENSE
Requires-Dist: requests>=2.25.1
Requires-Dist: web3
Requires-Dist: python-dateutil
Requires-Dist: requests
